setup.py
recast_api.egg-info/PKG-INFO
recast_api.egg-info/SOURCES.txt
recast_api.egg-info/dependency_links.txt
recast_api.egg-info/entry_points.txt
recast_api.egg-info/requires.txt
recast_api.egg-info/top_level.txt
recastapi/__init__.py
recastapi/apicli.py
recastapi/settings.py
recastapi/analysis/__init__.py
recastapi/analysis/read.py
recastapi/analysis/write.py
recastapi/request/__init__.py
recastapi/request/read.py
recastapi/request/write.py
recastapi/response/__init__.py
recastapi/response/read.py
recastapi/response/write.py
recastapi/user/__init__.py
recastapi/user/read.py
tests/__init__.py
tests/test_files.py
tests/test_response.py