Metadata-Version: 1.0
Name: recast-api
Version: 0.1.0
Summary: RECAST API
Home-page: http://github.com/recast-hep/recast-api
Author: Kyle Cranmer, Lukas Heinrich
Author-email: cranmer@cern.ch, lukas.heinrich@cern.ch
License: UNKNOWN
Platform: UNKNOWN
